requirements.txt
setup.py
gaiatest/__init__.py
gaiatest/cli.py
gaiatest/environment.py
gaiatest/file_manager.py
gaiatest/gaia_graphics_test.py
gaiatest/gaia_test.py
gaiatest/gcli.py
gaiatest/runtests.py
gaiatest/version.py
gaiatest.egg-info/PKG-INFO
gaiatest.egg-info/SOURCES.txt
gaiatest.egg-info/dependency_links.txt
gaiatest.egg-info/entry_points.txt
gaiatest.egg-info/not-zip-safe
gaiatest.egg-info/requires.txt
gaiatest.egg-info/top_level.txt
gaiatest/apps/__init__.py
gaiatest/apps/base.py
gaiatest/apps/bzlite/__init__.py
gaiatest/apps/bzlite/app.py
gaiatest/apps/calendar/__init__.py
gaiatest/apps/calendar/app.py
gaiatest/apps/calendar/regions/__init__.py
gaiatest/apps/calendar/regions/event.py
gaiatest/apps/calendar/regions/event_details.py
gaiatest/apps/camera/__init__.py
gaiatest/apps/camera/app.py
gaiatest/apps/clock/__init__.py
gaiatest/apps/clock/app.py
gaiatest/apps/clock/regions/__init__.py
gaiatest/apps/clock/regions/alarm.py
gaiatest/apps/clock/regions/alarm_alert.py
gaiatest/apps/clock/regions/new_alarm.py
gaiatest/apps/clock/regions/stopwatch.py
gaiatest/apps/clock/regions/stopwatch_timepicker.py
gaiatest/apps/clock/regions/timer.py
gaiatest/apps/contacts/__init__.py
gaiatest/apps/contacts/app.py
gaiatest/apps/contacts/regions/__init__.py
gaiatest/apps/contacts/regions/contact_details.py
gaiatest/apps/contacts/regions/contact_form.py
gaiatest/apps/contacts/regions/contact_import_picker.py
gaiatest/apps/contacts/regions/gmail.py
gaiatest/apps/contacts/regions/merge.py
gaiatest/apps/contacts/regions/set_ice_contacts.py
gaiatest/apps/contacts/regions/settings_form.py
gaiatest/apps/cost_control/__init__.py
gaiatest/apps/cost_control/app.py
gaiatest/apps/cost_control/regions/__init__.py
gaiatest/apps/cost_control/regions/ftu_step1.py
gaiatest/apps/cost_control/regions/ftu_step2.py
gaiatest/apps/cost_control/regions/ftu_step3.py
gaiatest/apps/cost_control/regions/settings.py
gaiatest/apps/email/__init__.py
gaiatest/apps/email/app.py
gaiatest/apps/email/regions/__init__.py
gaiatest/apps/email/regions/google.py
gaiatest/apps/email/regions/new_email.py
gaiatest/apps/email/regions/read_email.py
gaiatest/apps/email/regions/settings.py
gaiatest/apps/email/regions/setup.py
