Metadata-Version: 1.0
Name: gaiatest
Version: 0.34
Summary: Marionette test automation client for Gaia
Home-page: https://developer.mozilla.org/en-US/docs/Marionette
Author: Jonathan Griffin
Author-email: jgriffin@mozilla.com
License: MPL
Keywords: mozilla
Platform: UNKNOWN
